Metadata-Version: 1.1
Name: stockwebscraper
Version: 0.2.2
Summary: Use this to scrape stock prices
Home-page: https://github.com/YT-The-Scripting-Legend/StockWebScraperPipPkg
Author: The Scripting Legend
Author-email: thescriptinglegend@gmail.com
License: MIT
Keywords: STOCKS,STOCK,STOCK MARKET,WEB,SCRAPING,WEB SCRAPING
Platform: UNKNOWN
Classifier: Development Status :: 3 - Alpha
Classifier: Intended Audience :: Developers
Classifier: Topic :: Software Development :: Build Tools
Classifier: License :: OSI Approved :: MIT License
Classifier: Programming Language :: Python :: 3
Classifier: Programming Language :: Python :: 3.4
Classifier: Programming Language :: Python :: 3.5
Classifier: Programming Language :: Python :: 3.6
Classifier: Programming Language :: Python :: 3.7
Classifier: Programming Language :: Python :: 3.8
Classifier: Programming Language :: Python :: 3.9
